odoo9_addon_crm_claim_rma_code-9.0.1.0.0-py2.7-nspkg.pth
odoo_addons/crm_claim_rma_code/__openerp__.py
odoo_addons/crm_claim_rma_code/__init__.py
odoo_addons/crm_claim_rma_code/README.rst
odoo_addons/crm_claim_rma_code/models/__init__.py
odoo_addons/crm_claim_rma_code/models/crm_claim_type.py
odoo_addons/crm_claim_rma_code/i18n/es.po
odoo_addons/crm_claim_rma_code/i18n/es_VE.po
odoo_addons/crm_claim_rma_code/i18n/es_MX.po
odoo_addons/crm_claim_rma_code/i18n/crm_claim_rma_code.pot
odoo_addons/crm_claim_rma_code/i18n/es_PA.po
odoo_addons/crm_claim_rma_code/views/crm_claim_type.xml
odoo_addons/crm_claim_rma_code/data/ir_sequence_type.xml
odoo9_addon_crm_claim_rma_code-9.0.1.0.0.dist-info/top_level.txt
odoo9_addon_crm_claim_rma_code-9.0.1.0.0.dist-info/WHEEL
odoo9_addon_crm_claim_rma_code-9.0.1.0.0.dist-info/RECORD
odoo9_addon_crm_claim_rma_code-9.0.1.0.0.dist-info/metadata.json
odoo9_addon_crm_claim_rma_code-9.0.1.0.0.dist-info/DESCRIPTION.rst
odoo9_addon_crm_claim_rma_code-9.0.1.0.0.dist-info/METADATA
odoo9_addon_crm_claim_rma_code-9.0.1.0.0.dist-info/namespace_packages.txt
