Metadata-Version: 2.0
Name: odoo9-addon-crm-claim-rma-code
Version: 9.0.1.0.0
Summary: CRM Claim RMA Code
Home-page: http://www.vauxoo.com/
Author: UNKNOWN
Author-email: UNKNOWN
License: AGPL-3
Platform: UNKNOWN
Requires-Dist: odoo (<9.1a,>=9.0a)
Requires-Dist: odoo9-addon-crm-claim-code
Requires-Dist: odoo9-addon-crm-claim-type
Classifier: Programming Language :: Python :: 2.7
Classifier: Framework :: Odoo
Classifier: License :: OSI Approved :: GNU Affero General Public License v3
